itk_splitcomponents-2.2.4.dist-info/METADATA
itk_splitcomponents-2.2.4.dist-info/WHEEL
itk_splitcomponents-2.2.4.dist-info/RECORD
itk_splitcomponents-2.2.4.dist-info/licenses/LICENSE
itk/_SplitComponentsPython.abi3.so
itk/SplitComponentsPython.py
itk/itkSplitComponentsImageFilterPython.py
itk/Configuration/SplitComponentsConfig.py
itk/Configuration/SplitComponents_snake_case.py
itk_splitcomponents.libs/libtbb-e046f41a.so.12.9
