Metadata-Version: 2.1
Name: itk-splitcomponents
Version: 2.2.4
Summary: ITK filters to split a multi-component pixel image into component-wise scalar images
Keywords: itk
Author-Email: "Matthew M. McCormick" <matt.mccormick@kitware.com>
License: 
Classifier: Development Status :: 4 - Beta
Classifier: Intended Audience :: Developers
Classifier: Intended Audience :: Education
Classifier: Intended Audience :: Healthcare Industry
Classifier: Intended Audience :: Science/Research
Classifier: License :: OSI Approved :: Apache Software License
Classifier: Operating System :: Android
Classifier: Operating System :: MacOS
Classifier: Operating System :: Microsoft :: Windows
Classifier: Operating System :: POSIX
Classifier: Operating System :: Unix
Classifier: Programming Language :: C++
Classifier: Programming Language :: Python
Classifier: Topic :: Scientific/Engineering
Classifier: Topic :: Scientific/Engineering :: Information Analysis
Classifier: Topic :: Scientific/Engineering :: Medical Science Apps.
Classifier: Topic :: Software Development :: Libraries
Project-URL: Download, https://github.com/InsightSoftwareConsortium/ITKSplitComponents
Project-URL: Homepage, https://github.com/InsightSoftwareConsortium/ITKSplitComponents
Requires-Python: >=3.9
Requires-Dist: itk==5.4.*
